CMakeLists.txt
LICENSE
MANIFEST.in
README.md
pyproject.toml
setup.py
nle/.clang-format
nle/.flake8
nle/.git
nle/.gitattributes
nle/.gitignore
nle/.gitmodules
nle/.pre-commit-config.yaml
nle/.travis.yml
nle/CITATION.cff
nle/CMakeLists.txt
nle/CODE_OF_CONDUCT.md
nle/CONTRIBUTING.md
nle/DATASET.md
nle/Files
nle/Files.nh
nle/Files.nle
nle/LICENSE
nle/MANIFEST.in
nle/Porting
nle/README.md
nle/README.nh
nle/pyproject.toml
nle/setup.py
nle/version.txt
nle/.circleci/config.yml
nle/.github/pr-labeler.yml
nle/.github/release-drafter.yml
nle/.github/ISSUE_TEMPLATE/bug-report.md
nle/.github/ISSUE_TEMPLATE/feature-request.md
nle/.github/workflows/build_docker.yml
nle/.github/workflows/check_license.yml
nle/.github/workflows/lint_cc.yml
nle/.github/workflows/lint_python.yml
nle/.github/workflows/pr-labeler.yml
nle/.github/workflows/release-drafter.yml
nle/.github/workflows/test_and_deploy.yml
nle/.github/workflows/test_package.yml
nle/DEVEL/.gitattributes
nle/DEVEL/Developer.txt
nle/DEVEL/code_features.txt
nle/DEVEL/code_style.txt
nle/DEVEL/git_recipes.txt
nle/DEVEL/gitinfo.pl
nle/DEVEL/nhgitset.pl
nle/DEVEL/DOTGIT/TARGET
nle/DEVEL/hooksdir/NHadd
nle/DEVEL/hooksdir/NHgithook.pm
nle/DEVEL/hooksdir/NHsubst
nle/DEVEL/hooksdir/NHtext
nle/DEVEL/hooksdir/TARGET
nle/DEVEL/hooksdir/applypatch-msg
nle/DEVEL/hooksdir/commit-msg
nle/DEVEL/hooksdir/nhsub
nle/DEVEL/hooksdir/post-applypatch
nle/DEVEL/hooksdir/post-checkout
nle/DEVEL/hooksdir/post-commit
nle/DEVEL/hooksdir/post-merge
nle/DEVEL/hooksdir/post-rewrite
nle/DEVEL/hooksdir/pre-applypatch
nle/DEVEL/hooksdir/pre-auto-gc
nle/DEVEL/hooksdir/pre-commit
nle/DEVEL/hooksdir/pre-push
nle/DEVEL/hooksdir/pre-rebase
nle/DEVEL/hooksdir/prepare-commit-msg
nle/__pycache__/setup.cpython-39.pyc
nle/dat/.gitattributes
nle/dat/.gitignore
nle/dat/Arch.des
nle/dat/Barb.des
nle/dat/CMakeLists.txt
nle/dat/Caveman.des
nle/dat/GENFILES
nle/dat/Healer.des
nle/dat/Knight.des
nle/dat/Monk.des
nle/dat/Priest.des
nle/dat/Ranger.des
nle/dat/Rogue.des
nle_language_wrapper.egg-info/PKG-INFO
nle_language_wrapper.egg-info/SOURCES.txt
nle_language_wrapper.egg-info/dependency_links.txt
nle_language_wrapper.egg-info/requires.txt
nle_language_wrapper.egg-info/top_level.txt
