Metadata-Version: 2.1
Name: nle-language-wrapper
Version: 0.2.0
Summary: Language Wrapper for the NetHack Learning Environment (NLE) 
Home-page: https://github.com/ngoodger/nle-language-wrapper
Author: Nikolaj Goodger
License: MIT License
Platform: UNKNOWN
Classifier: License :: OSI Approved :: MIT License
Classifier: Development Status :: 2 - Pre-Alpha
Classifier: Operating System :: POSIX :: Linux
Classifier: Operating System :: MacOS
Classifier: Programming Language :: Python :: 3
Classifier: Programming Language :: Python :: 3.7
Classifier: Programming Language :: Python :: 3.8
Classifier: Programming Language :: Python :: 3.9
Classifier: Programming Language :: Python :: 3.10
Classifier: Programming Language :: C++
Classifier: Topic :: Scientific/Engineering :: Artificial Intelligence
Classifier: Topic :: Games/Entertainment
Requires-Python: >=3.7
Provides-Extra: dev
Provides-Extra: agent
License-File: LICENSE
